leann_backend_diskann/__init__.py
leann_backend_diskann/diskann_embedding_server.py
leann_backend_diskann/_diskannpy.cpython-310-darwin.so
leann_backend_diskann/graph_partition.py
leann_backend_diskann/diskann_backend.py
leann_backend_diskann/embedding_pb2.py
leann_backend_diskann/.dylibs/libabsl_tracing_internal.2508.0.0.dylib
leann_backend_diskann/.dylibs/libabsl_random_internal_platform.2508.0.0.dylib
leann_backend_diskann/.dylibs/libutf8_validity.33.2.0.dylib
leann_backend_diskann/.dylibs/libabsl_log_internal_conditions.2508.0.0.dylib
leann_backend_diskann/.dylibs/libabsl_decode_rust_punycode.2508.0.0.dylib
leann_backend_diskann/.dylibs/libabsl_flags_commandlineflag.2508.0.0.dylib
leann_backend_diskann/.dylibs/libabsl_random_seed_sequences.2508.0.0.dylib
leann_backend_diskann/.dylibs/libabsl_random_distributions.2508.0.0.dylib
leann_backend_diskann/.dylibs/libabsl_random_internal_randen_slow.2508.0.0.dylib
leann_backend_diskann/.dylibs/libabsl_flags_private_handle_accessor.2508.0.0.dylib
leann_backend_diskann/.dylibs/libprotobuf.33.2.0.dylib
leann_backend_diskann/.dylibs/libabsl_string_view.2508.0.0.dylib
leann_backend_diskann/.dylibs/libabsl_hashtablez_sampler.2508.0.0.dylib
leann_backend_diskann/.dylibs/libabsl_log_internal_structured_proto.2508.0.0.dylib
leann_backend_diskann/.dylibs/libabsl_exponential_biased.2508.0.0.dylib
leann_backend_diskann/.dylibs/libabsl_hash.2508.0.0.dylib
leann_backend_diskann/.dylibs/libabsl_log_internal_globals.2508.0.0.dylib
leann_backend_diskann/.dylibs/libabsl_statusor.2508.0.0.dylib
leann_backend_diskann/.dylibs/libabsl_stacktrace.2508.0.0.dylib
leann_backend_diskann/.dylibs/libabsl_time_zone.2508.0.0.dylib
leann_backend_diskann/.dylibs/libabsl_die_if_null.2508.0.0.dylib
leann_backend_diskann/.dylibs/libabsl_log_internal_format.2508.0.0.dylib
leann_backend_diskann/.dylibs/libabsl_strerror.2508.0.0.dylib
leann_backend_diskann/.dylibs/libabsl_log_sink.2508.0.0.dylib
leann_backend_diskann-0.3.6.dist-info/RECORD
leann_backend_diskann-0.3.6.dist-info/WHEEL
leann_backend_diskann-0.3.6.dist-info/METADATA
