Metadata-Version: 2.2
Name: leann-backend-diskann
Version: 0.3.6
Requires-Dist: leann-core==0.3.6
Requires-Dist: numpy
Requires-Dist: protobuf>=3.19.0
